aioelasticsearch_fork/__init__.py
aioelasticsearch_fork/connection.py
aioelasticsearch_fork/exceptions.py
aioelasticsearch_fork/helpers.py
aioelasticsearch_fork/pool.py
aioelasticsearch_fork/transport.py
aioelasticsearch_fork-0.0.1.dist-info/LICENSE
aioelasticsearch_fork-0.0.1.dist-info/METADATA
aioelasticsearch_fork-0.0.1.dist-info/WHEEL
aioelasticsearch_fork-0.0.1.dist-info/top_level.txt
aioelasticsearch_fork-0.0.1.dist-info/RECORD
